modulitiz_rpi/ModuloGPIOInput.py
modulitiz_rpi/adc/ModuloAdcAds1115.py
modulitiz_rpi/adc/ModuloAdcNtc.py
modulitiz_rpi-2.3.0.dist-info/licenses/LICENSE
modulitiz_rpi-2.3.0.dist-info/METADATA
modulitiz_rpi-2.3.0.dist-info/WHEEL
modulitiz_rpi-2.3.0.dist-info/top_level.txt
modulitiz_rpi-2.3.0.dist-info/RECORD
