Metadata-Version: 2.4
Name: modulitiz_rpi
Version: 2.3.0
Summary: Raccolta dei miei moduli - funzioni specifiche per il RaspberryPi
Author-email: tiz <sderfo1234@altervista.org>
Classifier: Programming Language :: Python :: 3
Classifier: Operating System :: OS Independent
Requires-Python: >=3.11
License-File: LICENSE
Requires-Dist: modulitiz-micro>=2
Requires-Dist: RPi.GPIO==0.7.1
Requires-Dist: types-RPi.GPIO==0.7.0.20250318
Requires-Dist: adafruit-circuitpython-ads1x15==2.2.4
Dynamic: license-file
